atlas/__init__.py
atlas/types.py
atlas/cli/env.py
atlas/cli/export.py
atlas/cli/jsonl_writer.py
atlas/cli/main.py
atlas/cli/persistence.py
atlas/cli/quickstart.py
atlas/cli/review.py
atlas/cli/run.py
atlas/cli/storage_runtime.py
atlas/cli/train.py
atlas/cli/utils.py
atlas/config/__init__.py
atlas/config/loader.py
atlas/config/models.py
atlas/config/schema.py
atlas/config/validation.py
atlas/connectors/__init__.py
atlas/connectors/factory.py
atlas/connectors/http.py
atlas/connectors/langchain_bridge.py
atlas/connectors/litellm.py
atlas/connectors/openai.py
atlas/connectors/prompt_digest.py
atlas/connectors/python.py
atlas/connectors/registry.py
atlas/connectors/utils.py
atlas/core/__init__.py
atlas/data/__init__.py
atlas/data/reward_eval_trajectories.jsonl
atlas/data/sample_probe_payloads.jsonl
atlas/data/sample_traces.jsonl
atlas/data/synthetic_runtime_tasks.jsonl
atlas/data_models/__init__.py
atlas/data_models/intermediate_step.py
atlas/data_models/invocation_node.py
atlas/evaluation/__init__.py
atlas/evaluation/evaluator.py
atlas/evaluation/learning_report.py
atlas/evaluation/judges/__init__.py
atlas/evaluation/judges/base.py
atlas/evaluation/judges/prompts.py
atlas/learning/__init__.py
atlas/learning/playbook.py
atlas/learning/playbook_entries.py
atlas/learning/prompts.py
atlas/learning/synthesizer.py
atlas/learning/usage.py
atlas/personas/__init__.py
atlas/personas/student.py
atlas/personas/teacher.py
atlas/prompts/__init__.py
atlas/prompts/system.py
atlas/runtime/__init__.py
atlas/runtime/learning_history.py
atlas/runtime/schema.py
atlas/runtime/adaptive/__init__.py
atlas/runtime/adaptive/probe.py
atlas/runtime/agent_loop/__init__.py
atlas/runtime/agent_loop/base_agent.py
atlas/runtime/agent_loop/dual_node.py
atlas/runtime/agent_loop/retries.py
atlas/runtime/agent_loop/tool_loop.py
atlas/runtime/learning/__init__.py
atlas/runtime/learning/drift.py
atlas/runtime/models/__init__.py
atlas/runtime/models/intermediate_step.py
atlas/runtime/models/invocation_node.py
arc_atlas-0.1.14.dist-info/METADATA
arc_atlas-0.1.14.dist-info/WHEEL
arc_atlas-0.1.14.dist-info/entry_points.txt
arc_atlas-0.1.14.dist-info/top_level.txt
arc_atlas-0.1.14.dist-info/RECORD
